logchange/__init__.py
logchange/__main__.py
logchange/changelog.py
logchange/cli_parser.py
logchange/constants.py
logchange/eol_fixer.py
logchange/executor.py
logchange/main.py
logchange/py.typed
logchange/record.py
logchange/record_body.py
logchange/record_section.py
logchange/utils.py
tests/__init__.py
tests/test_record_body.py
tests/test_utils.py
logchange-0.2.0.dist-info/LICENSE
logchange-0.2.0.dist-info/METADATA
logchange-0.2.0.dist-info/WHEEL
logchange-0.2.0.dist-info/entry_points.txt
logchange-0.2.0.dist-info/top_level.txt
logchange-0.2.0.dist-info/RECORD
