Metadata-Version: 2.1
Name: logchange
Version: 0.2.0
Summary: Keep-a-changelog manager
Home-page: https://github.com/vemel/logchange
Author: Vlad Emelianov
Author-email: vlad.emelianov.nz@gmail.com
License: MIT
Project-URL: Documentation, https://logchange.readthedocs.io/en/latest/
Project-URL: Source, https://github.com/vemel/logchange
Project-URL: Tracker, https://github.com/vemel/logchange/issues
Keywords: keep-a-changelog,ci,automation
Platform: UNKNOWN
Classifier: Development Status :: 5 - Production/Stable
Classifier: Environment :: Console
Classifier: License :: OSI Approved :: MIT License
Classifier: Natural Language :: English
Classifier: Operating System :: OS Independent
Classifier: Programming Language :: Python :: 3
Classifier: Programming Language :: Python :: 3.6
Classifier: Programming Language :: Python :: 3.7
Classifier: Programming Language :: Python :: 3.8
Classifier: Programming Language :: Python :: 3.9
Classifier: Programming Language :: Python :: 3 :: Only
Classifier: Programming Language :: Python :: Implementation :: CPython
Classifier: Typing :: Typed
Classifier: Topic :: Software Development :: Libraries :: Python Modules
Requires-Dist: newversion
Requires-Dist: typing-extensions
